Metadata-Version: 2.1
Name: odoo13-addon-sale-stock-analytic
Version: 13.0.1.0.1.dev2
Summary: Copies the analytic account of the sale order and the analytic tags of the sale order line to the stock move
Home-page: https://github.com/OCA/account-analytic
Author: ACSONE SA/NV,Odoo Community Association (OCA)
Author-email: support@odoo-community.org
License: AGPL-3
Platform: UNKNOWN
Classifier: Programming Language :: Python
Classifier: Framework :: Odoo
Classifier: Framework :: Odoo :: 13.0
Classifier: License :: OSI Approved :: GNU Affero General Public License v3
Requires-Python: >=3.5
Requires-Dist: odoo13-addon-stock-analytic
Requires-Dist: odoo (<13.1dev,>=13.0a)
